cliffy/__init__.py
cliffy/__main__.py
cliffy/ai.py
cliffy/blueprint.py
cliffy/builder.py
cliffy/cli.py
cliffy/commander.py
cliffy/doc.py
cliffy/helper.py
cliffy/homer.py
cliffy/loader.py
cliffy/manifest.py
cliffy/merger.py
cliffy/parser.py
cliffy/py.typed
cliffy/reloader.py
cliffy/rich.py
cliffy/run.py
cliffy/tester.py
cliffy/transformer.py
cliffy/commanders/__init__.py
cliffy/commanders/click.py
cliffy/commanders/typer.py
cliffy-0.6.1.dist-info/METADATA
cliffy-0.6.1.dist-info/WHEEL
cliffy-0.6.1.dist-info/entry_points.txt
cliffy-0.6.1.dist-info/licenses/LICENSE
cliffy-0.6.1.dist-info/RECORD
