Metadata-Version: 2.4
Name: cliffy
Version: 0.6.1
Summary: $ cli load from.yaml
Project-URL: Documentation, https://jaykv.github.io/cliffy/
Project-URL: Repository, https://github.com/jaykv/cliffy
Author-email: Jay <jay.github0@gmail.com>
License-Expression: MIT
License-File: LICENSE
Requires-Python: >=3.9
Requires-Dist: click>=8.1.0
Requires-Dist: deepmerge>=1.1.0
Requires-Dist: jinja2>=3.1.2
Requires-Dist: packaging>=23.1
Requires-Dist: pybash>=0.3.4
Requires-Dist: pydantic>=2.6.1
Requires-Dist: pyyaml>=6.0
Requires-Dist: shiv>=1.0.3
Requires-Dist: typer-slim>=0.12.3
Requires-Dist: watchdog>=4.0.1
Provides-Extra: ai
Requires-Dist: pydantic-ai>=0.0.19; extra == 'ai'
Provides-Extra: dev
Requires-Dist: mypy>=1.14.1; extra == 'dev'
Requires-Dist: pytest-cov>=6.0.0; extra == 'dev'
Requires-Dist: pytest-mock>=3.14.0; extra == 'dev'
Requires-Dist: pytest-pretty>=1.2.0; extra == 'dev'
Requires-Dist: pytest-xdist>=3.6.1; extra == 'dev'
Requires-Dist: pytest>=8.3.4; extra == 'dev'
Requires-Dist: ruff>=0.9.1; extra == 'dev'
Requires-Dist: tabulate>=0.9.0; extra == 'dev'
Provides-Extra: rich
Requires-Dist: rich-click>=1.6.1; extra == 'rich'
Requires-Dist: shellingham>=1.5.0; extra == 'rich'
